{
  "extends": ["tslint:latest", "tslint-react", "tslint-plugin-prettier", "tslint-config-prettier"],
  "rules": {
    "array-type": [true, "generic"],
    "align": [true, "parameters", "statements"],
    "interface-name": false,
    "max-line-length": [true, 88],
    "no-console": false,
    "no-implicit-dependencies": [	
      true,	
      ["components", "routes", "theme"]	
    ],
    "no-submodule-imports": false,
    "object-literal-sort-keys": false,
    "ordered-imports": false,
    "prettier": true,
    "quotemark": [true, "single", "jsx-single"],
    "semicolon": [true, "never"]
  }
}
